{
    "Version": "4.2.0",
    "ScreenshotData": {
        "Cell_Field_CellField_3D_0": {
            "Plot": {
                "PlotType": "CellField",
                "PlotName": "Cell_Field"
            },
            "Dimension": "3D",
            "Projection": {
                "ProjectionPlane": null,
                "ProjectionPosition": null
            },
            "CameraClippingRange": {
                "Min": "189.14950902523927",
                "Max": "587.3090007649018"
            },
            "CameraFocalPoint": {
                "x": "100.0",
                "y": "100.0",
                "z": "0.0"
            },
            "CameraPosition": {
                "x": "-163.75461104578523",
                "y": "-147.97986298242944",
                "z": "269.9310395663156"
            },
            "CameraViewUp": {
                "x": "-0.28519476932511323",
                "y": "0.8282985859338983",
                "z": "0.48227108153972914"
            },
            "Size": {
                "Width": 600,
                "Height": 600
            },
            "CellBorders": true,
            "Cells": true,
            "ClusterBorders": false,
            "CellGlyphs": false,
            "FPPLinks": false,
            "BoundingBox": true,
            "LatticeAxes": true,
            "LatticeAxesLabels": true,
            "TypesInvisible": [
                0
            ],
            "metadata": {
                "BorderColor": [
                    255,
                    255,
                    0,
                    255
                ],
                "ClusterBorderColor": [
                    0,
                    0,
                    255,
                    255
                ],
                "BoundingBoxColor": [
                    255,
                    255,
                    255,
                    255
                ],
                "AxesColor": [
                    255,
                    255,
                    255,
                    255
                ],
                "ContourColor": [
                    255,
                    255,
                    255,
                    255
                ],
                "WindowColor": [
                    0,
                    0,
                    0,
                    255
                ],
                "FPPLinksColor": [
                    255,
                    255,
                    255,
                    255
                ],
                "ShowHorizontalAxesLabels": true,
                "ShowVerticalAxesLabels": true,
                "TypeColorMap": {
                    "0": [
                        0,
                        0,
                        0,
                        255
                    ],
                    "1": [
                        0,
                        0,
                        255,
                        255
                    ],
                    "2": [
                        0,
                        128,
                        0,
                        255
                    ],
                    "3": [
                        255,
                        0,
                        0,
                        255
                    ],
                    "4": [
                        255,
                        255,
                        0,
                        255
                    ],
                    "5": [
                        165,
                        42,
                        42,
                        255
                    ],
                    "6": [
                        173,
                        216,
                        230,
                        255
                    ],
                    "7": [
                        144,
                        238,
                        144,
                        255
                    ],
                    "8": [
                        128,
                        0,
                        128,
                        255
                    ],
                    "9": [
                        255,
                        165,
                        0,
                        255
                    ],
                    "10": [
                        64,
                        224,
                        208,
                        255
                    ]
                }
            }
        }
    }
}